songci/__init__.py
songci/__main__.py
songci/__version__.py
songci/api.py
songci/helper.py
songci-0.1.3.dist-info/LICENSE
songci-0.1.3.dist-info/METADATA
songci-0.1.3.dist-info/WHEEL
songci-0.1.3.dist-info/entry_points.txt
songci-0.1.3.dist-info/top_level.txt
songci-0.1.3.dist-info/RECORD
